snakemake_interface_executor_plugins/__init__.py
snakemake_interface_executor_plugins/_common.py
snakemake_interface_executor_plugins/cli.py
snakemake_interface_executor_plugins/dag.py
snakemake_interface_executor_plugins/executors/__init__.py
snakemake_interface_executor_plugins/executors/base.py
snakemake_interface_executor_plugins/executors/jobscript.sh
snakemake_interface_executor_plugins/executors/real.py
snakemake_interface_executor_plugins/executors/remote.py
snakemake_interface_executor_plugins/jobs.py
snakemake_interface_executor_plugins/logging.py
snakemake_interface_executor_plugins/persistence.py
snakemake_interface_executor_plugins/registry/__init__.py
snakemake_interface_executor_plugins/registry/plugin.py
snakemake_interface_executor_plugins/scheduler.py
snakemake_interface_executor_plugins/settings.py
snakemake_interface_executor_plugins/utils.py
snakemake_interface_executor_plugins/workflow.py
snakemake_interface_executor_plugins-9.3.9.dist-info/LICENSE
snakemake_interface_executor_plugins-9.3.9.dist-info/METADATA
snakemake_interface_executor_plugins-9.3.9.dist-info/WHEEL
snakemake_interface_executor_plugins-9.3.9.dist-info/RECORD
