Metadata-Version: 2.3
Name: snakemake-interface-executor-plugins
Version: 9.3.9
Summary: This package provides a stable interface for interactions between Snakemake and its executor plugins.
License: MIT
Author: Johannes Köster
Author-email: johannes.koester@uni-due.de
Requires-Python: >=3.11
Classifier: License :: OSI Approved :: MIT License
Classifier: Programming Language :: Python :: 3
Classifier: Programming Language :: Python :: 3.11
Classifier: Programming Language :: Python :: 3.12
Classifier: Programming Language :: Python :: 3.13
Requires-Dist: argparse-dataclass (>=2.0.0)
Requires-Dist: snakemake-interface-common (>=1.19.0)
Requires-Dist: throttler (>=1.2.2)
